work.py
work_components/__init__.py
work_components/arguments.py
work_components/consts.py
work_components/container.py
work_components/dao/__init__.py
work_components/dao/core.py
work_components/dao/flags.py
work_components/dao/rc.py
work_components/dao/recess.py
work_components/dt_parse.py
work_components/migrate.py
work_components/protocols.py
work_components/timestamps.py
work_components/util.py
work_time_log-0.101.1.dist-info/METADATA
work_time_log-0.101.1.dist-info/WHEEL
work_time_log-0.101.1.dist-info/entry_points.txt
work_time_log-0.101.1.dist-info/RECORD
