Metadata-Version: 2.1
Name: work-time-log
Version: 0.101.1
Summary: Manual time tracking via a CLI that works similarly to git.
Home-page: https://vauhoch.zett.cc/work/
Author: Valentin
Author-email: noemail@example.com
Requires-Python: >=3.8,<4.0
Classifier: Programming Language :: Python :: 3
Classifier: Programming Language :: Python :: 3.8
Classifier: Programming Language :: Python :: 3.9
Classifier: Programming Language :: Python :: 3.10
Classifier: Programming Language :: Python :: 3.11
